{
    "txs": [
        {
            "time": 1535439486,
            "valueOut": 59522.02162305,
            "size": 226,
            "confirmations": 4993,
            "vout": [
                {
                    "scriptPubKey": {
                        "type": "pubkeyhash",
                        "asm": "OP_DUP OP_HASH160 1ae63514e742b9cfbebae46f1b95257f1c2c417d OP_EQUALVERIFY OP_CHECKSIG",
                        "addresses": [
                            "MAMPaWEgdRmRupgybTB7ZGWDeLH2m4XxaJ"
                        ],
                        "reqSigs": 1
                    },
                    "spentIndex": 0,
                    "spentTs": 1535467836,
                    "spentTxId": "44cc01d341bf6b3059e10b9eb148194f29f2e03053032b4684065b0bac950e66",
                    "n": 0,
                    "value": "58532.02162305"
                },
                {
                    "scriptPubKey": {
                        "type": "pubkeyhash",
                        "asm": "OP_DUP OP_HASH160 0c4af7ff5e1f246bd138f65d7075bed311859c5c OP_EQUALVERIFY OP_CHECKSIG",
                        "addresses": [
                            "M92A9ek5745jKDveURpmKzagwe1pCDkVeM"
                        ],
                        "reqSigs": 1
                    },
                    "spentIndex": 4,
                    "spentTs": 1535522022,
                    "spentTxId": "1046f81f07532a4fb85868a9ff6cad7a5da6d771fb06ecba2f567a25c5d67cc7",
                    "n": 1,
                    "value": "990.00000000"
                }
            ],
            "valueIn": 59522.02614305,
            "vin": [
                {
                    "vout": 0,
                    "doubleSpentTxID": null,
                    "txid": "b3283374c5b304cdbe3041e39d880a390ffe11d51ded6c58b1f91b9b77eba1d9",
                    "addr": "MJpHGCYzeXMLX7edHH46VeNNp68e1yv7Yx",
                    "value": 59522.02614305,
                    "sequence": 4294967294,
                    "n": 0,
                    "scriptSig": {
                        "asm": "3045022100c88c517288251537319309eff620b831c5813dbc7ca6f349351c662f3ad41967022004449e7f30d2be9bf73bbf30ad84af74540ab4b0177ec2a69604434f52ef401101 0245aabd2a0c435f99ac1c72a3e89f8a0a441c0197603dffd0912a95cd71ff3146"
                    },
                    "valueSat": 5952202614305
                }
            ],
            "txid": "77fe21b048c3649d620460c9051781917ea2e9e31fe279ff939374385df48166",
            "fees": 0.00452,
            "blockhash": "5aed177aa2f4e3e483eb83514767de6d069e367d51523b017d1ca82cf6260e25",
            "version": 2,
            "locktime": 1423528,
            "blocktime": 1535439486
        },
        {
            "time": 1535522022,
            "valueOut": 4727.997,
            "size": 816,
            "confirmations": 4119,
            "vout": [
                {
                    "scriptPubKey": {
                        "type": "pubkeyhash",
                        "asm": "OP_DUP OP_HASH160 580131bd78acf5d5dad8a0dd882a78ecd00efd07 OP_EQUALVERIFY OP_CHECKSIG",
                        "addresses": [
                            "MFvV8HvDtWQxXfjDBLiYAhjUjdUzBTFTiN"
                        ],
                        "reqSigs": 1
                    },
                    "spentIndex": 21,
                    "spentTs": 1535526808,
                    "spentTxId": "2ea2b762296de0ada8bcbd79134370b5f24f7684d679e29321325b0fd87868dd",
                    "n": 0,
                    "value": "727.99700000"
                },
                {
                    "scriptPubKey": {
                        "type": "pubkeyhash",
                        "asm": "OP_DUP OP_HASH160 89dbde79a6a3a218267376a8541d2ac9e89af735 OP_EQUALVERIFY OP_CHECKSIG",
                        "addresses": [
                            "MLU6CUnkgTQ6DWznDoN1Smog5R15iuZ9Uo"
                        ],
                        "reqSigs": 1
                    },
                    "spentIndex": 0,
                    "spentTs": 1535523233,
                    "spentTxId": "6802877449c203ea97096f378e3b12e4130098959a044fd2a807052225888cbf",
                    "n": 1,
                    "value": "4000.00000000"
                }
            ],
            "valueIn": 4727.998,
            "vin": [
                {
                    "vout": 0,
                    "doubleSpentTxID": null,
                    "txid": "762ee5549d2f0557d94e080d40c693e0476bbf9af7fdf256074480f8fd9aec36",
                    "addr": "MHLYxrmQYkQyfgTtTAdb3TTpsvbPwDSHLw",
                    "value": 969.999,
                    "sequence": 4294967295,
                    "n": 0,
                    "scriptSig": {
                        "asm": "3045022100caa23d3f55eb855e564b429477d2b640c0abebcbfe5c6065a6a7a2528c91e59e02203c003508e8714135379bc4661a843bef9d7004e112d29073656781e99027788501 021080788776e2a9c827018c4d06c57e9037b9928f1cff53c6f892593d8e5a6458"
                    },
                    "valueSat": 96999900000
                },
                {
                    "vout": 1,
                    "doubleSpentTxID": null,
                    "txid": "b3283374c5b304cdbe3041e39d880a390ffe11d51ded6c58b1f91b9b77eba1d9",
                    "addr": "M92A9ek5745jKDveURpmKzagwe1pCDkVeM",
                    "value": 990,
                    "sequence": 4294967295,
                    "n": 1,
                    "scriptSig": {
                        "asm": "30440220692791bb90fd851166309026a1fbbd6d015b36b3b920414a526615bbe67ffd1f0220569ca14a0ba334f1d8de77a8fef1f0f67666d54b79f8f54e9561ddbbc2c8ac0501 0314b95e9b42ea325167b546087280e79de051cae2599a85389662b8a2d28720c3"
                    },
                    "valueSat": 99000000000
                },
                {
                    "vout": 0,
                    "doubleSpentTxID": null,
                    "txid": "9b18700493ae29e8d381a687b09be228389669194d72c44ac86e72435c469992",
                    "addr": "M92A9ek5745jKDveURpmKzagwe1pCDkVeM",
                    "value": 990,
                    "sequence": 4294967295,
                    "n": 2,
                    "scriptSig": {
                        "asm": "304402202cc193a6043b8dd9df63d19fefd7f12d5fedd1aa37d7177f0a6d1f80fb0a64df022062711239964df41b94e87a3a119cff3aa21963d10c2c55167804c12d2fef855d01 0314b95e9b42ea325167b546087280e79de051cae2599a85389662b8a2d28720c3"
                    },
                    "valueSat": 99000000000
                },
                {
                    "vout": 0,
                    "doubleSpentTxID": null,
                    "txid": "d5a038776201582aff762938852cb52af28d5c8df7b1cda5f84b7ed45ecb9420",
                    "addr": "MMCfHozN8CUAcp6fAjJdoodcjfzj7W89p4",
                    "value": 787.999,
                    "sequence": 4294967295,
                    "n": 3,
                    "scriptSig": {
                        "asm": "3045022100b76df09497b5cb294870cfea1fc5a77fc18b6d9d2a24ad6d5007cca4a822ad3c02207c3b6d4eae2498bd38a57cc8181f7ad6786015cb7e3324f6dca68a045e76fc0501 0366d6c87c1be80f994cd2daec0363f2c8199fabcc341edcd5e78a1179cc61144f"
                    },
                    "valueSat": 78799900000
                },
                {
                    "vout": 1,
                    "doubleSpentTxID": null,
                    "txid": "77fe21b048c3649d620460c9051781917ea2e9e31fe279ff939374385df48166",
                    "addr": "M92A9ek5745jKDveURpmKzagwe1pCDkVeM",
                    "value": 990,
                    "sequence": 4294967295,
                    "n": 4,
                    "scriptSig": {
                        "asm": "3045022100ac84943f9f60791e8d7fc0ab2668a0c788f2173299b550911df0ca20ef975459022071882872c37752cb5432cd382d12c8c0c4f4dc852583eaf528d82bf7a5cff6c801 0314b95e9b42ea325167b546087280e79de051cae2599a85389662b8a2d28720c3"
                    },
                    "valueSat": 99000000000
                }
            ],
            "txid": "1046f81f07532a4fb85868a9ff6cad7a5da6d771fb06ecba2f567a25c5d67cc7",
            "fees": 0.001,
            "blockhash": "89a1f66fa0c5f13a4f9e720404040062088aab377e5e2226fa37f23fe959d6be",
            "version": 1,
            "locktime": 0,
            "blocktime": 1535522022
        },
        {
            "time": 1535439486,
            "valueOut": 999.99548,
            "size": 225,
            "confirmations": 4993,
            "vout": [
                {
                    "scriptPubKey": {
                        "type": "pubkeyhash",
                        "asm": "OP_DUP OP_HASH160 0c4af7ff5e1f246bd138f65d7075bed311859c5c OP_EQUALVERIFY OP_CHECKSIG",
                        "addresses": [
                            "M92A9ek5745jKDveURpmKzagwe1pCDkVeM"
                        ],
                        "reqSigs": 1
                    },
                    "spentIndex": 2,
                    "spentTs": 1535522022,
                    "spentTxId": "1046f81f07532a4fb85868a9ff6cad7a5da6d771fb06ecba2f567a25c5d67cc7",
                    "n": 0,
                    "value": "990.00000000"
                },
                {
                    "scriptPubKey": {
                        "type": "pubkeyhash",
                        "asm": "OP_DUP OP_HASH160 5e3cc33df0eff9de8a1640d5e7dd48c854d35dab OP_EQUALVERIFY OP_CHECKSIG",
                        "addresses": [
                            "MGVSYKsRJ5WYtH2vdPaeEsGgZgGieuKDJa"
                        ],
                        "reqSigs": 1
                    },
                    "spentIndex": 4,
                    "spentTs": 1535458553,
                    "spentTxId": "f91432f913bb29a553d2fcf16fa54f6321a836934267430cf17bffba6e4f4588",
                    "n": 1,
                    "value": "9.99548000"
                }
            ],
            "valueIn": 1000,
            "vin": [
                {
                    "vout": 1,
                    "doubleSpentTxID": null,
                    "txid": "44057d22f35084d0a09073c8d2ff3096917f241a4ff07f4ebc522d34e2c7512f",
                    "addr": "MLU6CUnkgTQ6DWznDoN1Smog5R15iuZ9Uo",
                    "value": 1000,
                    "sequence": 4294967294,
                    "n": 0,
                    "scriptSig": {
                        "asm": "3044022036572dbbd1df0f0450d1aba2452c38028e03a359d41cf73e1d95772cc2530be802200f8134505868ed85ce9d02707294beb2e54918c6f38818963988afc8f2dbf5ba01 02981be1626ce241810428f04173173486ebffcb0ca3913ce696e2c1b05eaee4f3"
                    },
                    "valueSat": 100000000000
                }
            ],
            "txid": "9b18700493ae29e8d381a687b09be228389669194d72c44ac86e72435c469992",
            "fees": 0.00452,
            "blockhash": "5aed177aa2f4e3e483eb83514767de6d069e367d51523b017d1ca82cf6260e25",
            "version": 2,
            "locktime": 1423527,
            "blocktime": 1535439486
        },
        {
            "time": 1535439486,
            "valueOut": 60512.02614305,
            "size": 226,
            "confirmations": 4993,
            "vout": [
                {
                    "scriptPubKey": {
                        "type": "pubkeyhash",
                        "asm": "OP_DUP OP_HASH160 77bd2c2ed9ebb9194a20afb51133dc020d9d72b2 OP_EQUALVERIFY OP_CHECKSIG",
                        "addresses": [
                            "MJpHGCYzeXMLX7edHH46VeNNp68e1yv7Yx"
                        ],
                        "reqSigs": 1
                    },
                    "spentIndex": 0,
                    "spentTs": 1535439486,
                    "spentTxId": "77fe21b048c3649d620460c9051781917ea2e9e31fe279ff939374385df48166",
                    "n": 0,
                    "value": "59522.02614305"
                },
                {
                    "scriptPubKey": {
                        "type": "pubkeyhash",
                        "asm": "OP_DUP OP_HASH160 0c4af7ff5e1f246bd138f65d7075bed311859c5c OP_EQUALVERIFY OP_CHECKSIG",
                        "addresses": [
                            "M92A9ek5745jKDveURpmKzagwe1pCDkVeM"
                        ],
                        "reqSigs": 1
                    },
                    "spentIndex": 1,
                    "spentTs": 1535522022,
                    "spentTxId": "1046f81f07532a4fb85868a9ff6cad7a5da6d771fb06ecba2f567a25c5d67cc7",
                    "n": 1,
                    "value": "990.00000000"
                }
            ],
            "valueIn": 60512.03066305,
            "vin": [
                {
                    "vout": 1,
                    "doubleSpentTxID": null,
                    "txid": "a6229a764af8dbc39d79b0a08634c3c4d94b6b978ca6a340e133dfb2176f128f",
                    "addr": "MMJKeY5uMd4PqYucPuNjF6uTb99J4bLdk9",
                    "value": 60512.03066305,
                    "sequence": 4294967294,
                    "n": 0,
                    "scriptSig": {
                        "asm": "3045022100e2d46544b429c1a7adf2af3937fb296debb79039c672ccc8f4a28188199f7b43022014d9d4f36cd2d40a22e035dbca73ea5440499535b6dda2e42fb1cb9ed9f815c301 0336136eba6793d9c48e4346adc8b86cc7295b05da5860b57ecaf59829b3443e22"
                    },
                    "valueSat": 6051203066305
                }
            ],
            "txid": "b3283374c5b304cdbe3041e39d880a390ffe11d51ded6c58b1f91b9b77eba1d9",
            "fees": 0.00452,
            "blockhash": "5aed177aa2f4e3e483eb83514767de6d069e367d51523b017d1ca82cf6260e25",
            "version": 2,
            "locktime": 1423528,
            "blocktime": 1535439486
        },
        {
            "time": 1535435577,
            "valueOut": 63482.03970305,
            "size": 226,
            "confirmations": 5040,
            "vout": [
                {
                    "scriptPubKey": {
                        "type": "pubkeyhash",
                        "asm": "OP_DUP OP_HASH160 4f906d692a3c9fd35eb3717b0416e64762ff0c2b OP_EQUALVERIFY OP_CHECKSIG",
                        "addresses": [
                            "MF9rdaLCxQdbfHSMpsQSqjYLAxBpJPgXN3"
                        ],
                        "reqSigs": 1
                    },
                    "spentIndex": 0,
                    "spentTs": 1535435577,
                    "spentTxId": "4a77ce1adf3217e2bcc78d4c79ddbf7a31f1e712313e9c878cb1681e62fa646c",
                    "n": 0,
                    "value": "62492.03970305"
                },
                {
                    "scriptPubKey": {
                        "type": "pubkeyhash",
                        "asm": "OP_DUP OP_HASH160 0c4af7ff5e1f246bd138f65d7075bed311859c5c OP_EQUALVERIFY OP_CHECKSIG",
                        "addresses": [
                            "M92A9ek5745jKDveURpmKzagwe1pCDkVeM"
                        ],
                        "reqSigs": 1
                    },
                    "spentIndex": 0,
                    "spentTs": 1535514981,
                    "spentTxId": "65c973f25969d79e5f4940e7a4dda4a0f3557a021642992bfc524476212b80be",
                    "n": 1,
                    "value": "990.00000000"
                }
            ],
            "valueIn": 63482.04422305,
            "vin": [
                {
                    "vout": 1,
                    "doubleSpentTxID": null,
                    "txid": "db617c199f067ced6e70ecebd2dd44ac151a0fc576f03ad454bb7f5cccbd2069",
                    "addr": "MMj4KWv2sE9aDt9PcnS8bQvhXgDyeH6r1o",
                    "value": 63482.04422305,
                    "sequence": 4294967294,
                    "n": 0,
                    "scriptSig": {
                        "asm": "3045022100859a30970779f572a2267c0cc4ddde02e79ae59007e558e0869d3718b39ae8cc0220420c257d60dca13859b7e49bf712ac8348010768976fecf08a25a2d7218c61ad01 028bf6d34c39a0e421bee15b5c2041c71b94eaa2e232f98e32e9d49d3928f2de44"
                    },
                    "valueSat": 6348204422305
                }
            ],
            "txid": "0745d99cd3be3522e3e72fa445f7092df184adce32257de9919010e3c1c57f70",
            "fees": 0.00452,
            "blockhash": "9dcd021da0492a8e70bc680656bd1a6973b14cde926c229e5bc8ff63beede552",
            "version": 2,
            "locktime": 1423481,
            "blocktime": 1535435577
        },
        {
            "time": 1535514981,
            "valueOut": 2969.999,
            "size": 520,
            "confirmations": 4198,
            "vout": [
                {
                    "scriptPubKey": {
                        "type": "pubkeyhash",
                        "asm": "OP_DUP OP_HASH160 45aa5adc640fdafdbe89dea833f7012879e8c031 OP_EQUALVERIFY OP_CHECKSIG",
                        "addresses": [
                            "MEFWw8jjoKYHkFDsxw1C6VNx2AoSZ4d4iU"
                        ],
                        "reqSigs": 1
                    },
                    "spentIndex": 20,
                    "spentTs": 1535526808,
                    "spentTxId": "2ea2b762296de0ada8bcbd79134370b5f24f7684d679e29321325b0fd87868dd",
                    "n": 0,
                    "value": "969.99900000"
                },
                {
                    "scriptPubKey": {
                        "type": "pubkeyhash",
                        "asm": "OP_DUP OP_HASH160 89dbde79a6a3a218267376a8541d2ac9e89af735 OP_EQUALVERIFY OP_CHECKSIG",
                        "addresses": [
                            "MLU6CUnkgTQ6DWznDoN1Smog5R15iuZ9Uo"
                        ],
                        "reqSigs": 1
                    },
                    "spentIndex": 0,
                    "spentTs": 1535516055,
                    "spentTxId": "390487491cc234f9e59cbd88d3611c9287be0c2dae0110015c930693395ed3bb",
                    "n": 1,
                    "value": "2000.00000000"
                }
            ],
            "valueIn": 2970,
            "vin": [
                {
                    "vout": 1,
                    "doubleSpentTxID": null,
                    "txid": "0745d99cd3be3522e3e72fa445f7092df184adce32257de9919010e3c1c57f70",
                    "addr": "M92A9ek5745jKDveURpmKzagwe1pCDkVeM",
                    "value": 990,
                    "sequence": 4294967295,
                    "n": 0,
                    "scriptSig": {
                        "asm": "304402205aae172d07b20bedcdd3142c922272f4d3194850afe6f6673af7b3b58937ff35022069f7c2678a2af1c405d470ca810d769b717b4ab383a4ede6ba0ecd3cd04c0ead01 0314b95e9b42ea325167b546087280e79de051cae2599a85389662b8a2d28720c3"
                    },
                    "valueSat": 99000000000
                },
                {
                    "vout": 0,
                    "doubleSpentTxID": null,
                    "txid": "a6229a764af8dbc39d79b0a08634c3c4d94b6b978ca6a340e133dfb2176f128f",
                    "addr": "M92A9ek5745jKDveURpmKzagwe1pCDkVeM",
                    "value": 990,
                    "sequence": 4294967295,
                    "n": 1,
                    "scriptSig": {
                        "asm": "3045022100ef7ce08bdb1b9749512a5a1da86fc13673669d2bde0f01f1d7fd21259d0708ca02205410f28a9dfff677e49955f0313121fc16b07b9c150b309c6d2766d2754a0a3001 0314b95e9b42ea325167b546087280e79de051cae2599a85389662b8a2d28720c3"
                    },
                    "valueSat": 99000000000
                },
                {
                    "vout": 0,
                    "doubleSpentTxID": null,
                    "txid": "4a77ce1adf3217e2bcc78d4c79ddbf7a31f1e712313e9c878cb1681e62fa646c",
                    "addr": "M92A9ek5745jKDveURpmKzagwe1pCDkVeM",
                    "value": 990,
                    "sequence": 4294967295,
                    "n": 2,
                    "scriptSig": {
                        "asm": "3044022061da414fd7e1b846c138cd429ba84e44fae45db267387a3fe0f9b1fa61f6a4a402202d040f5317b328a9c31b22fd1c24c3836e551d21c251e23d7c5e5e692633ffb801 0314b95e9b42ea325167b546087280e79de051cae2599a85389662b8a2d28720c3"
                    },
                    "valueSat": 99000000000
                }
            ],
            "txid": "65c973f25969d79e5f4940e7a4dda4a0f3557a021642992bfc524476212b80be",
            "fees": 0.001,
            "blockhash": "c260bb2c74b33dcc184d39d75b959b9fad2fb83d0e01ac7fc6a7771df5e1e3e4",
            "version": 1,
            "locktime": 0,
            "blocktime": 1535514981
        },
        {
            "time": 1535435577,
            "valueOut": 62492.03518305,
            "size": 225,
            "confirmations": 5040,
            "vout": [
                {
                    "scriptPubKey": {
                        "type": "pubkeyhash",
                        "asm": "OP_DUP OP_HASH160 0c4af7ff5e1f246bd138f65d7075bed311859c5c OP_EQUALVERIFY OP_CHECKSIG",
                        "addresses": [
                            "M92A9ek5745jKDveURpmKzagwe1pCDkVeM"
                        ],
                        "reqSigs": 1
                    },
                    "spentIndex": 2,
                    "spentTs": 1535514981,
                    "spentTxId": "65c973f25969d79e5f4940e7a4dda4a0f3557a021642992bfc524476212b80be",
                    "n": 0,
                    "value": "990.00000000"
                },
                {
                    "scriptPubKey": {
                        "type": "pubkeyhash",
                        "asm": "OP_DUP OP_HASH160 b998db8ed06a9e08edd52411d1f8e6864004fbb0 OP_EQUALVERIFY OP_CHECKSIG",
                        "addresses": [
                            "MQpWMeucSvUChYaZw4C7FqKPgDJoq4ey7r"
                        ],
                        "reqSigs": 1
                    },
                    "spentIndex": 0,
                    "spentTs": 1535435577,
                    "spentTxId": "a6229a764af8dbc39d79b0a08634c3c4d94b6b978ca6a340e133dfb2176f128f",
                    "n": 1,
                    "value": "61502.03518305"
                }
            ],
            "valueIn": 62492.03970305,
            "vin": [
                {
                    "vout": 0,
                    "doubleSpentTxID": null,
                    "txid": "0745d99cd3be3522e3e72fa445f7092df184adce32257de9919010e3c1c57f70",
                    "addr": "MF9rdaLCxQdbfHSMpsQSqjYLAxBpJPgXN3",
                    "value": 62492.03970305,
                    "sequence": 4294967294,
                    "n": 0,
                    "scriptSig": {
                        "asm": "304402205e13878f61712c0dc128e8a64a9abe84a245356592113d23fb3e5ea4a6d3af970220141907375954a117c46057a5ce21e79be5eee8b1c1811996481ed26d1f3844ec01 030a292fddaedd0b249e7e3c1a6f647f50e115c0a373d9e7e177fb559fdafe2e9d"
                    },
                    "valueSat": 6249203970305
                }
            ],
            "txid": "4a77ce1adf3217e2bcc78d4c79ddbf7a31f1e712313e9c878cb1681e62fa646c",
            "fees": 0.00452,
            "blockhash": "9dcd021da0492a8e70bc680656bd1a6973b14cde926c229e5bc8ff63beede552",
            "version": 2,
            "locktime": 1423481,
            "blocktime": 1535435577
        },
        {
            "time": 1535435577,
            "valueOut": 61502.03066305,
            "size": 225,
            "confirmations": 5040,
            "vout": [
                {
                    "scriptPubKey": {
                        "type": "pubkeyhash",
                        "asm": "OP_DUP OP_HASH160 0c4af7ff5e1f246bd138f65d7075bed311859c5c OP_EQUALVERIFY OP_CHECKSIG",
                        "addresses": [
                            "M92A9ek5745jKDveURpmKzagwe1pCDkVeM"
                        ],
                        "reqSigs": 1
                    },
                    "spentIndex": 1,
                    "spentTs": 1535514981,
                    "spentTxId": "65c973f25969d79e5f4940e7a4dda4a0f3557a021642992bfc524476212b80be",
                    "n": 0,
                    "value": "990.00000000"
                },
                {
                    "scriptPubKey": {
                        "type": "pubkeyhash",
                        "asm": "OP_DUP OP_HASH160 92fb0fe4a84e0490bc677f08be9c0ac0260b0a06 OP_EQUALVERIFY OP_CHECKSIG",
                        "addresses": [
                            "MMJKeY5uMd4PqYucPuNjF6uTb99J4bLdk9"
                        ],
                        "reqSigs": 1
                    },
                    "spentIndex": 0,
                    "spentTs": 1535439486,
                    "spentTxId": "b3283374c5b304cdbe3041e39d880a390ffe11d51ded6c58b1f91b9b77eba1d9",
                    "n": 1,
                    "value": "60512.03066305"
                }
            ],
            "valueIn": 61502.03518305,
            "vin": [
                {
                    "vout": 1,
                    "doubleSpentTxID": null,
                    "txid": "4a77ce1adf3217e2bcc78d4c79ddbf7a31f1e712313e9c878cb1681e62fa646c",
                    "addr": "MQpWMeucSvUChYaZw4C7FqKPgDJoq4ey7r",
                    "value": 61502.03518305,
                    "sequence": 4294967294,
                    "n": 0,
                    "scriptSig": {
                        "asm": "304402206de6407bb4aed2d17a62f2b4b538dedca54a247a882d228f8775acebce8c090b0220175ec58bcf8896d7d8a4039583c8b7512be5f757f3fe21331eca8b391f8c537801 03e487bdcb9a9b9029991e7fc828205c7308bac406b10f6adff0d1580ac5dfd92a"
                    },
                    "valueSat": 6150203518305
                }
            ],
            "txid": "a6229a764af8dbc39d79b0a08634c3c4d94b6b978ca6a340e133dfb2176f128f",
            "fees": 0.00452,
            "blockhash": "9dcd021da0492a8e70bc680656bd1a6973b14cde926c229e5bc8ff63beede552",
            "version": 2,
            "locktime": 1423481,
            "blocktime": 1535435577
        },
        {
            "time": 1535435577,
            "valueOut": 64472.04422305,
            "size": 225,
            "confirmations": 5040,
            "vout": [
                {
                    "scriptPubKey": {
                        "type": "pubkeyhash",
                        "asm": "OP_DUP OP_HASH160 0c4af7ff5e1f246bd138f65d7075bed311859c5c OP_EQUALVERIFY OP_CHECKSIG",
                        "addresses": [
                            "M92A9ek5745jKDveURpmKzagwe1pCDkVeM"
                        ],
                        "reqSigs": 1
                    },
                    "spentIndex": 2,
                    "spentTs": 1535516987,
                    "spentTxId": "a28d7b8efb6f73db24cd3a570527e2426b0e36904cd0b9edda856ade0563f57e",
                    "n": 0,
                    "value": "990.00000000"
                },
                {
                    "scriptPubKey": {
                        "type": "pubkeyhash",
                        "asm": "OP_DUP OP_HASH160 97a8aa7fcbeb4522fe9d6efe01349febce313b47 OP_EQUALVERIFY OP_CHECKSIG",
                        "addresses": [
                            "MMj4KWv2sE9aDt9PcnS8bQvhXgDyeH6r1o"
                        ],
                        "reqSigs": 1
                    },
                    "spentIndex": 0,
                    "spentTs": 1535435577,
                    "spentTxId": "0745d99cd3be3522e3e72fa445f7092df184adce32257de9919010e3c1c57f70",
                    "n": 1,
                    "value": "63482.04422305"
                }
            ],
            "valueIn": 64472.04874305,
            "vin": [
                {
                    "vout": 1,
                    "doubleSpentTxID": null,
                    "txid": "44f483fd3ef0e0b0b8abbcbcc89998249acf6afa1fbc2c1796bf7a0964b54d76",
                    "addr": "M7uPAAZV6f4T5JYBZDTi6JHMQUDPxpaxpD",
                    "value": 64472.04874305,
                    "sequence": 4294967294,
                    "n": 0,
                    "scriptSig": {
                        "asm": "304402204775a7a1299523f5759361444e8de03e4e1057b2c9d10c054129983bb2c478c402202547d483f8646716b4bb5630a8e819684e29e4eccc6b4d3f7904451a82738bea01 021f46851aae4c2ca9464ed484df1c7504c390d48b656d676b0068d2cd93295313"
                    },
                    "valueSat": 6447204874305
                }
            ],
            "txid": "db617c199f067ced6e70ecebd2dd44ac151a0fc576f03ad454bb7f5cccbd2069",
            "fees": 0.00452,
            "blockhash": "9dcd021da0492a8e70bc680656bd1a6973b14cde926c229e5bc8ff63beede552",
            "version": 2,
            "locktime": 1423480,
            "blocktime": 1535435577
        },
        {
            "time": 1535516987,
            "valueOut": 2804.865,
            "size": 520,
            "confirmations": 4181,
            "vout": [
                {
                    "scriptPubKey": {
                        "type": "pubkeyhash",
                        "asm": "OP_DUP OP_HASH160 5548e4948fe7b9c4ae3d8296ed7b75da09eef7a1 OP_EQUALVERIFY OP_CHECKSIG",
                        "addresses": [
                            "MFg6zRUBoZKXAbPLXzKaRcK9WwDZRbeUxU"
                        ],
                        "reqSigs": 1
                    },
                    "spentIndex": 29,
                    "spentTs": 1535526808,
                    "spentTxId": "2ea2b762296de0ada8bcbd79134370b5f24f7684d679e29321325b0fd87868dd",
                    "n": 0,
                    "value": "804.86500000"
                },
                {
                    "scriptPubKey": {
                        "type": "pubkeyhash",
                        "asm": "OP_DUP OP_HASH160 89dbde79a6a3a218267376a8541d2ac9e89af735 OP_EQUALVERIFY OP_CHECKSIG",
                        "addresses": [
                            "MLU6CUnkgTQ6DWznDoN1Smog5R15iuZ9Uo"
                        ],
                        "reqSigs": 1
                    },
                    "spentIndex": 0,
                    "spentTs": 1535518685,
                    "spentTxId": "d6d79005a953034279d70a2679def8ed009e11f98e41251bf8b36a9a6bca633c",
                    "n": 1,
                    "value": "2000.00000000"
                }
            ],
            "valueIn": 2804.866,
            "vin": [
                {
                    "vout": 0,
                    "doubleSpentTxID": null,
                    "txid": "147baf62261ba8949c69081c3050d20f7cbb4a5cab915cc54915516f60d9a6d5",
                    "addr": "M92A9ek5745jKDveURpmKzagwe1pCDkVeM",
                    "value": 834.867,
                    "sequence": 4294967295,
                    "n": 0,
                    "scriptSig": {
                        "asm": "30440220494faba14aa4cfa6c6d220d6399b3f9513222112edb6c932a8ed68d4ce167f20022064461ff2e007a91c339265ce33a137405af367890b70c72f26902c029b176a6901 0314b95e9b42ea325167b546087280e79de051cae2599a85389662b8a2d28720c3"
                    },
                    "valueSat": 83486700000
                },
                {
                    "vout": 0,
                    "doubleSpentTxID": null,
                    "txid": "44057d22f35084d0a09073c8d2ff3096917f241a4ff07f4ebc522d34e2c7512f",
                    "addr": "MCUL7on4PdM1Rkm7k3wDStZ76ChVGWs4RZ",
                    "value": 979.999,
                    "sequence": 4294967295,
                    "n": 1,
                    "scriptSig": {
                        "asm": "3044022055bbf19abcd6028312daad90bc07e4792a1a0f4b2d489fc535e775df802ce79802202e906f2ff4c6fca527e97cb33bec629feb8785a59ed01ad3f2714d42cd8955e001 023693b578344c49a92d571768d0c589e1dbd1420691a0551aeab213c2a229492f"
                    },
                    "valueSat": 97999900000
                },
                {
                    "vout": 0,
                    "doubleSpentTxID": null,
                    "txid": "db617c199f067ced6e70ecebd2dd44ac151a0fc576f03ad454bb7f5cccbd2069",
                    "addr": "M92A9ek5745jKDveURpmKzagwe1pCDkVeM",
                    "value": 990,
                    "sequence": 4294967295,
                    "n": 2,
                    "scriptSig": {
                        "asm": "3045022100f509d6af4e54b9f949e54e2e943f6cf8f9521851af46ce31603bb7187036886d022035c1091ca76d8ba8467b7e31395660c2316ce190a388ce594b4f0cf50266ad2801 0314b95e9b42ea325167b546087280e79de051cae2599a85389662b8a2d28720c3"
                    },
                    "valueSat": 99000000000
                }
            ],
            "txid": "a28d7b8efb6f73db24cd3a570527e2426b0e36904cd0b9edda856ade0563f57e",
            "fees": 0.001,
            "blockhash": "46ec62a7b0ace28c34df148420f565d9b83a8d750afe25dac3828525cdb4b618",
            "version": 1,
            "locktime": 0,
            "blocktime": 1535516987
        },
        {
            "time": 1535435514,
            "valueOut": 65462.04874305,
            "size": 225,
            "confirmations": 5041,
            "vout": [
                {
                    "scriptPubKey": {
                        "type": "pubkeyhash",
                        "asm": "OP_DUP OP_HASH160 0c4af7ff5e1f246bd138f65d7075bed311859c5c OP_EQUALVERIFY OP_CHECKSIG",
                        "addresses": [
                            "M92A9ek5745jKDveURpmKzagwe1pCDkVeM"
                        ],
                        "reqSigs": 1
                    },
                    "spentIndex": 1,
                    "spentTs": 1535513456,
                    "spentTxId": "139e29ec011412177810ae8b979a37f93aab205f7438f4cc6047b4f24cf2aa2d",
                    "n": 0,
                    "value": "990.00000000"
                },
                {
                    "scriptPubKey": {
                        "type": "pubkeyhash",
                        "asm": "OP_DUP OP_HASH160 000aca5cac93f2f969ba276ce5458725bce00768 OP_EQUALVERIFY OP_CHECKSIG",
                        "addresses": [
                            "M7uPAAZV6f4T5JYBZDTi6JHMQUDPxpaxpD"
                        ],
                        "reqSigs": 1
                    },
                    "spentIndex": 0,
                    "spentTs": 1535435577,
                    "spentTxId": "db617c199f067ced6e70ecebd2dd44ac151a0fc576f03ad454bb7f5cccbd2069",
                    "n": 1,
                    "value": "64472.04874305"
                }
            ],
            "valueIn": 65462.05326305,
            "vin": [
                {
                    "vout": 1,
                    "doubleSpentTxID": null,
                    "txid": "fb6c291c0e4ebb74fbb48891aeb3b96de81d4b4137af18bedda7ef57968097ed",
                    "addr": "MBBtCuw5SHM7qJu6d6U2712GpzGMoPTNC5",
                    "value": 65462.05326305,
                    "sequence": 4294967294,
                    "n": 0,
                    "scriptSig": {
                        "asm": "3044022007b27c701fda26328996e7da50e9199969c5fa66f13973d98f65e16989c02af602203c377f604fbbdb3b158ef47b66498e292a2155fc9688042fa6020703887a333701 034d0c30f6082870f8e0aa682058bec18a2d3d740a5472a1759e9d03695f4a2379"
                    },
                    "valueSat": 6546205326305
                }
            ],
            "txid": "44f483fd3ef0e0b0b8abbcbcc89998249acf6afa1fbc2c1796bf7a0964b54d76",
            "fees": 0.00452,
            "blockhash": "2a5995cc126655b3b1f0f39ac371f317bb16ac568d4c4b512a8200be5cc54c2d",
            "version": 2,
            "locktime": 1423481,
            "blocktime": 1535435514
        },
        {
            "time": 1535513456,
            "valueOut": 2959.998,
            "size": 519,
            "confirmations": 4222,
            "vout": [
                {
                    "scriptPubKey": {
                        "type": "pubkeyhash",
                        "asm": "OP_DUP OP_HASH160 b1d974c90ebe092487f2992a41478bc77ee502fe OP_EQUALVERIFY OP_CHECKSIG",
                        "addresses": [
                            "MQ7YLWGCeU5xTLD8KMLegGQY23fQgGE5Q4"
                        ],
                        "reqSigs": 1
                    },
                    "spentIndex": 3,
                    "spentTs": 1535526808,
                    "spentTxId": "2ea2b762296de0ada8bcbd79134370b5f24f7684d679e29321325b0fd87868dd",
                    "n": 0,
                    "value": "959.99800000"
                },
                {
                    "scriptPubKey": {
                        "type": "pubkeyhash",
                        "asm": "OP_DUP OP_HASH160 89dbde79a6a3a218267376a8541d2ac9e89af735 OP_EQUALVERIFY OP_CHECKSIG",
                        "addresses": [
                            "MLU6CUnkgTQ6DWznDoN1Smog5R15iuZ9Uo"
                        ],
                        "reqSigs": 1
                    },
                    "spentIndex": 0,
                    "spentTs": 1535516055,
                    "spentTxId": "0faaa47c26e4f88a480fdba278c09127efea43840e336c067f02c9ed08ab2b57",
                    "n": 1,
                    "value": "2000.00000000"
                }
            ],
            "valueIn": 2959.999,
            "vin": [
                {
                    "vout": 0,
                    "doubleSpentTxID": null,
                    "txid": "74c21ac03b90d1ec81e1a69d2d65cbe80f10f542099ef69a72644e0bbb8808bc",
                    "addr": "M92A9ek5745jKDveURpmKzagwe1pCDkVeM",
                    "value": 990,
                    "sequence": 4294967295,
                    "n": 0,
                    "scriptSig": {
                        "asm": "304402205242b1ddda5b3bee05f9ac73bd00e03813d5f90ca233e77555f091ff0440ab8302205bab1290b79b9b360669d93513acb57bcf6414617339d3e4526dbee44ca8ade201 0314b95e9b42ea325167b546087280e79de051cae2599a85389662b8a2d28720c3"
                    },
                    "valueSat": 99000000000
                },
                {
                    "vout": 0,
                    "doubleSpentTxID": null,
                    "txid": "44f483fd3ef0e0b0b8abbcbcc89998249acf6afa1fbc2c1796bf7a0964b54d76",
                    "addr": "M92A9ek5745jKDveURpmKzagwe1pCDkVeM",
                    "value": 990,
                    "sequence": 4294967295,
                    "n": 1,
                    "scriptSig": {
                        "asm": "30440220760af81b57980383faba6aafb5f679276f694785b6373cf760545575a6a9ade202200af5b6ba83e605042b3107788f51822a1e234fdfc589b3c0164de035f413214e01 0314b95e9b42ea325167b546087280e79de051cae2599a85389662b8a2d28720c3"
                    },
                    "valueSat": 99000000000
                },
                {
                    "vout": 0,
                    "doubleSpentTxID": null,
                    "txid": "5f5bcc07692eb31fe7f5d1e7c2cba80f134a87139493008c6a7936fd326da671",
                    "addr": "M9h74q4TqA2QSdijGaJGBmcT4YVx4qmmQP",
                    "value": 979.999,
                    "sequence": 4294967295,
                    "n": 2,
                    "scriptSig": {
                        "asm": "304402204a3fd8b11c338520060392923e7d8f708151b879089f7555e0eee96b4019539102207e4996a45818d72d1cddf083d8dc3ec6858f0bb9c024ebc921788d4e6128f18901 026b90ec510449f471109ee8d850674dafd2ab08cdb7ae5846f527abca0c22a403"
                    },
                    "valueSat": 97999900000
                }
            ],
            "txid": "139e29ec011412177810ae8b979a37f93aab205f7438f4cc6047b4f24cf2aa2d",
            "fees": 0.001,
            "blockhash": "21fa285ef132bed88b67bfbf8f1d0536184d3ad9ca418091d0e26eefef643030",
            "version": 1,
            "locktime": 0,
            "blocktime": 1535513456
        },
        {
            "time": 1535435514,
            "valueOut": 999.99548,
            "size": 226,
            "confirmations": 5041,
            "vout": [
                {
                    "scriptPubKey": {
                        "type": "pubkeyhash",
                        "asm": "OP_DUP OP_HASH160 0c4af7ff5e1f246bd138f65d7075bed311859c5c OP_EQUALVERIFY OP_CHECKSIG",
                        "addresses": [
                            "M92A9ek5745jKDveURpmKzagwe1pCDkVeM"
                        ],
                        "reqSigs": 1
                    },
                    "spentIndex": 0,
                    "spentTs": 1535513456,
                    "spentTxId": "139e29ec011412177810ae8b979a37f93aab205f7438f4cc6047b4f24cf2aa2d",
                    "n": 0,
                    "value": "990.00000000"
                },
                {
                    "scriptPubKey": {
                        "type": "pubkeyhash",
                        "asm": "OP_DUP OP_HASH160 8228c0981e00c7210dbbdd54a4e48f2835055a7e OP_EQUALVERIFY OP_CHECKSIG",
                        "addresses": [
                            "MKmNttX2o7KGvPxeiHLhR6dAthNP2P594G"
                        ],
                        "reqSigs": 1
                    },
                    "spentIndex": 9,
                    "spentTs": 1535458553,
                    "spentTxId": "f91432f913bb29a553d2fcf16fa54f6321a836934267430cf17bffba6e4f4588",
                    "n": 1,
                    "value": "9.99548000"
                }
            ],
            "valueIn": 1000,
            "vin": [
                {
                    "vout": 1,
                    "doubleSpentTxID": null,
                    "txid": "5f5bcc07692eb31fe7f5d1e7c2cba80f134a87139493008c6a7936fd326da671",
                    "addr": "MLU6CUnkgTQ6DWznDoN1Smog5R15iuZ9Uo",
                    "value": 1000,
                    "sequence": 4294967294,
                    "n": 0,
                    "scriptSig": {
                        "asm": "3045022100c37c2aa4b51afc95f78d3808c05cb3d50800362e7ae22bfd642be4ac1e12339d02201d8ead6834fbe2ccdc33c440e6da21a136d853f41643d321e8345c563cb40c3301 02981be1626ce241810428f04173173486ebffcb0ca3913ce696e2c1b05eaee4f3"
                    },
                    "valueSat": 100000000000
                }
            ],
            "txid": "74c21ac03b90d1ec81e1a69d2d65cbe80f10f542099ef69a72644e0bbb8808bc",
            "fees": 0.00452,
            "blockhash": "2a5995cc126655b3b1f0f39ac371f317bb16ac568d4c4b512a8200be5cc54c2d",
            "version": 2,
            "locktime": 1423452,
            "blocktime": 1535435514
        },
        {
            "time": 1535423464,
            "valueOut": 69636.40634305,
            "size": 226,
            "confirmations": 5179,
            "vout": [
                {
                    "scriptPubKey": {
                        "type": "pubkeyhash",
                        "asm": "OP_DUP OP_HASH160 0c4af7ff5e1f246bd138f65d7075bed311859c5c OP_EQUALVERIFY OP_CHECKSIG",
                        "addresses": [
                            "M92A9ek5745jKDveURpmKzagwe1pCDkVeM"
                        ],
                        "reqSigs": 1
                    },
                    "spentIndex": 0,
                    "spentTs": 1535516987,
                    "spentTxId": "a28d7b8efb6f73db24cd3a570527e2426b0e36904cd0b9edda856ade0563f57e",
                    "n": 0,
                    "value": "834.86700000"
                },
                {
                    "scriptPubKey": {
                        "type": "pubkeyhash",
                        "asm": "OP_DUP OP_HASH160 54531b387df36a4d7411afb028de4418a412a40f OP_EQUALVERIFY OP_CHECKSIG",
                        "addresses": [
                            "MFb2Ysb9AmzxnfxyxYejCdvFTLHZLGx2SX"
                        ],
                        "reqSigs": 1
                    },
                    "spentIndex": 0,
                    "spentTs": 1535423464,
                    "spentTxId": "f4547de754fe481bd9ad85c64a1736726a270b41d9c5164f47794d7c797a19e9",
                    "n": 1,
                    "value": "68801.53934305"
                }
            ],
            "valueIn": 69636.41086305,
            "vin": [
                {
                    "vout": 1,
                    "doubleSpentTxID": null,
                    "txid": "cc4833cff4ab1e28b6101cb62029f016dd67a2f5b592064957ce16fe96c08ab5",
                    "addr": "MDSVHvNdqRYDqCWNaDKZcXEsUmjpbHMYFv",
                    "value": 69636.41086305,
                    "sequence": 4294967294,
                    "n": 0,
                    "scriptSig": {
                        "asm": "3045022100c816278e5adc97759a15fa4a2fd49e34cd3e1db9d2b9d9e6140b556a39687ac9022000a9bd25e9b25c7887abcfc9cbd32494eeec10f76e433a27d7fab289bade8e3b01 03aabab5a501683b7c72f3406245928718f9e851293d0fd7178f5385084ed208cc"
                    },
                    "valueSat": 6963641086305
                }
            ],
            "txid": "147baf62261ba8949c69081c3050d20f7cbb4a5cab915cc54915516f60d9a6d5",
            "fees": 0.00452,
            "blockhash": "eac47a6e978dcec1ec509bed55437cfb0eeba42f621acde8c8653ae068b68d14",
            "version": 2,
            "locktime": 1423343,
            "blocktime": 1535423464
        },
        {
            "time": 1535423464,
            "valueOut": 842.99548,
            "size": 226,
            "confirmations": 5179,
            "vout": [
                {
                    "scriptPubKey": {
                        "type": "pubkeyhash",
                        "asm": "OP_DUP OP_HASH160 99c181e6d6ffdbfc5ca10703726b583394572025 OP_EQUALVERIFY OP_CHECKSIG",
                        "addresses": [
                            "MMv9RurXF87Kvuj49PPMWmyyLVt6abwaQw"
                        ],
                        "reqSigs": 1
                    },
                    "spentIndex": 2,
                    "spentTs": 1535449793,
                    "spentTxId": "bdd39cb95326245d38935ea099475c6bb21d237333fcef586d0783f14273c332",
                    "n": 0,
                    "value": "8.12848000"
                },
                {
                    "scriptPubKey": {
                        "type": "pubkeyhash",
                        "asm": "OP_DUP OP_HASH160 0c4af7ff5e1f246bd138f65d7075bed311859c5c OP_EQUALVERIFY OP_CHECKSIG",
                        "addresses": [
                            "M92A9ek5745jKDveURpmKzagwe1pCDkVeM"
                        ],
                        "reqSigs": 1
                    },
                    "spentIndex": 2,
                    "spentTs": 1535520526,
                    "spentTxId": "01a1296ce5e08ef94cb0913d2f3895d19d06a690ed8c4346d9140a12a2578e40",
                    "n": 1,
                    "value": "834.86700000"
                }
            ],
            "valueIn": 843,
            "vin": [
                {
                    "vout": 1,
                    "doubleSpentTxID": null,
                    "txid": "dfaab812e75702a1ad5b2f09e59aa609aa92f03b01215a5f72545baa034be15f",
                    "addr": "MLU6CUnkgTQ6DWznDoN1Smog5R15iuZ9Uo",
                    "value": 843,
                    "sequence": 4294967294,
                    "n": 0,
                    "scriptSig": {
                        "asm": "3045022100ca3b11737fe73cc21e707b57130becf4c06102034608dda54c9505122e734e720220179f88c50d2c039fa9c91e8d4f8def7354f893b9ebe28433a2cb5890358c276901 02981be1626ce241810428f04173173486ebffcb0ca3913ce696e2c1b05eaee4f3"
                    },
                    "valueSat": 84300000000
                }
            ],
            "txid": "5d69325a4b3c0ae4bc3ff53819f45072c7f80dc6e64f1a7f1c4106cbe1054576",
            "fees": 0.00452,
            "blockhash": "eac47a6e978dcec1ec509bed55437cfb0eeba42f621acde8c8653ae068b68d14",
            "version": 2,
            "locktime": 1423343,
            "blocktime": 1535423464
        },
        {
            "time": 1535520526,
            "valueOut": 2504.6,
            "size": 520,
            "confirmations": 4142,
            "vout": [
                {
                    "scriptPubKey": {
                        "type": "pubkeyhash",
                        "asm": "OP_DUP OP_HASH160 89dbde79a6a3a218267376a8541d2ac9e89af735 OP_EQUALVERIFY OP_CHECKSIG",
                        "addresses": [
                            "MLU6CUnkgTQ6DWznDoN1Smog5R15iuZ9Uo"
                        ],
                        "reqSigs": 1
                    },
                    "spentIndex": 0,
                    "spentTs": 1535523233,
                    "spentTxId": "ffa173518787d4661f995d77733673b97ce8d7b361a94371b2fcd25626fe0736",
                    "n": 0,
                    "value": "2000.00000000"
                },
                {
                    "scriptPubKey": {
                        "type": "pubkeyhash",
                        "asm": "OP_DUP OP_HASH160 c70dde41494b8c9e26439510981e232faf739794 OP_EQUALVERIFY OP_CHECKSIG",
                        "addresses": [
                            "MS3fKBYyqEE9jy1bnorwVf8q3pj3A6Zv8L"
                        ],
                        "reqSigs": 1
                    },
                    "spentIndex": 10,
                    "spentTs": 1535526808,
                    "spentTxId": "2ea2b762296de0ada8bcbd79134370b5f24f7684d679e29321325b0fd87868dd",
                    "n": 1,
                    "value": "504.60000000"
                }
            ],
            "valueIn": 2504.601,
            "vin": [
                {
                    "vout": 1,
                    "doubleSpentTxID": null,
                    "txid": "caf1fc2430d3c0d5c0f6d0d68a0ea40ed8c3467006a85219a36531c070b49968",
                    "addr": "M92A9ek5745jKDveURpmKzagwe1pCDkVeM",
                    "value": 834.867,
                    "sequence": 4294967295,
                    "n": 0,
                    "scriptSig": {
                        "asm": "304402206b7f39141813e358459616f38e19baa918a304b984f7b8e0912077a3e3cefb7902200cf71a585adf7f0d611f828e2cb2655bd48fa490fc27f7a25a7092fd85bceb5d01 0314b95e9b42ea325167b546087280e79de051cae2599a85389662b8a2d28720c3"
                    },
                    "valueSat": 83486700000
                },
                {
                    "vout": 1,
                    "doubleSpentTxID": null,
                    "txid": "ad4d49bf44caabbee397d9d4e4d8308887b6fcc048f043b0711a1a30f2607fa0",
                    "addr": "M92A9ek5745jKDveURpmKzagwe1pCDkVeM",
                    "value": 834.867,
                    "sequence": 4294967295,
                    "n": 1,
                    "scriptSig": {
                        "asm": "3045022100b91a753e8203ab27cb35612104731ad387763d9bb946e158cd8ed85625f0d2420220343f03e86c88f6d30221778fa59fa44f1136302127e3e63357c498e0100eb90f01 0314b95e9b42ea325167b546087280e79de051cae2599a85389662b8a2d28720c3"
                    },
                    "valueSat": 83486700000
                },
                {
                    "vout": 1,
                    "doubleSpentTxID": null,
                    "txid": "5d69325a4b3c0ae4bc3ff53819f45072c7f80dc6e64f1a7f1c4106cbe1054576",
                    "addr": "M92A9ek5745jKDveURpmKzagwe1pCDkVeM",
                    "value": 834.867,
                    "sequence": 4294967295,
                    "n": 2,
                    "scriptSig": {
                        "asm": "304402205550f9d700494c4f42a1280756cd7abf1f253f23cbc623eb25707b2ad0cd6a29022063cc925e4df525fecfa33959dc18e7d120a5f65a110ed1d0903c8dc1ac87fa9001 0314b95e9b42ea325167b546087280e79de051cae2599a85389662b8a2d28720c3"
                    },
                    "valueSat": 83486700000
                }
            ],
            "txid": "01a1296ce5e08ef94cb0913d2f3895d19d06a690ed8c4346d9140a12a2578e40",
            "fees": 0.001,
            "blockhash": "d004a182a814234f6585d9f7cb7718053a38d544db08b874083e4c619f47fae1",
            "version": 1,
            "locktime": 0,
            "blocktime": 1535520526
        },
        {
            "time": 1535423464,
            "valueOut": 67131.79178305,
            "size": 225,
            "confirmations": 5179,
            "vout": [
                {
                    "scriptPubKey": {
                        "type": "pubkeyhash",
                        "asm": "OP_DUP OP_HASH160 2edba46661b8907e39dd5f02f87f674d92d2b96b OP_EQUALVERIFY OP_CHECKSIG",
                        "addresses": [
                            "MCAvSG6bBH7eqEhVjGS8VvsbRQKpKjb8ka"
                        ],
                        "reqSigs": 1
                    },
                    "spentIndex": 0,
                    "spentTs": 1535423464,
                    "spentTxId": "fb6c291c0e4ebb74fbb48891aeb3b96de81d4b4137af18bedda7ef57968097ed",
                    "n": 0,
                    "value": "66296.92478305"
                },
                {
                    "scriptPubKey": {
                        "type": "pubkeyhash",
                        "asm": "OP_DUP OP_HASH160 0c4af7ff5e1f246bd138f65d7075bed311859c5c OP_EQUALVERIFY OP_CHECKSIG",
                        "addresses": [
                            "M92A9ek5745jKDveURpmKzagwe1pCDkVeM"
                        ],
                        "reqSigs": 1
                    },
                    "spentIndex": 1,
                    "spentTs": 1535520526,
                    "spentTxId": "01a1296ce5e08ef94cb0913d2f3895d19d06a690ed8c4346d9140a12a2578e40",
                    "n": 1,
                    "value": "834.86700000"
                }
            ],
            "valueIn": 67131.79630305,
            "vin": [
                {
                    "vout": 0,
                    "doubleSpentTxID": null,
                    "txid": "caf1fc2430d3c0d5c0f6d0d68a0ea40ed8c3467006a85219a36531c070b49968",
                    "addr": "MAz4yB9fomamDijhSFL5BZ4bfMryEjUnVo",
                    "value": 67131.79630305,
                    "sequence": 4294967294,
                    "n": 0,
                    "scriptSig": {
                        "asm": "304402207c3c11f1647c2799797096e3ad97f0242d00cdd556650c9068e8cb5caff8979f02200b427efa861e7167b01721b80e7473607b4726cba892d86c6c0ef38af11612af01 02b428372d4c0f831a22068e29f1f43bd27df70fb35a450cd1f194f043b8600c33"
                    },
                    "valueSat": 6713179630305
                }
            ],
            "txid": "ad4d49bf44caabbee397d9d4e4d8308887b6fcc048f043b0711a1a30f2607fa0",
            "fees": 0.00452,
            "blockhash": "eac47a6e978dcec1ec509bed55437cfb0eeba42f621acde8c8653ae068b68d14",
            "version": 2,
            "locktime": 1423323,
            "blocktime": 1535423464
        },
        {
            "time": 1535423464,
            "valueOut": 67966.66330305,
            "size": 226,
            "confirmations": 5179,
            "vout": [
                {
                    "scriptPubKey": {
                        "type": "pubkeyhash",
                        "asm": "OP_DUP OP_HASH160 21d61056bf257c918944a3ea42b3684a106c1209 OP_EQUALVERIFY OP_CHECKSIG",
                        "addresses": [
                            "MAz4yB9fomamDijhSFL5BZ4bfMryEjUnVo"
                        ],
                        "reqSigs": 1
                    },
                    "spentIndex": 0,
                    "spentTs": 1535423464,
                    "spentTxId": "ad4d49bf44caabbee397d9d4e4d8308887b6fcc048f043b0711a1a30f2607fa0",
                    "n": 0,
                    "value": "67131.79630305"
                },
                {
                    "scriptPubKey": {
                        "type": "pubkeyhash",
                        "asm": "OP_DUP OP_HASH160 0c4af7ff5e1f246bd138f65d7075bed311859c5c OP_EQUALVERIFY OP_CHECKSIG",
                        "addresses": [
                            "M92A9ek5745jKDveURpmKzagwe1pCDkVeM"
                        ],
                        "reqSigs": 1
                    },
                    "spentIndex": 0,
                    "spentTs": 1535520526,
                    "spentTxId": "01a1296ce5e08ef94cb0913d2f3895d19d06a690ed8c4346d9140a12a2578e40",
                    "n": 1,
                    "value": "834.86700000"
                }
            ],
            "valueIn": 67966.66782305,
            "vin": [
                {
                    "vout": 0,
                    "doubleSpentTxID": null,
                    "txid": "f4547de754fe481bd9ad85c64a1736726a270b41d9c5164f47794d7c797a19e9",
                    "addr": "MCrtyQQ1x1PfnUornekdt2sJ5SVKyFUvZw",
                    "value": 67966.66782305,
                    "sequence": 4294967294,
                    "n": 0,
                    "scriptSig": {
                        "asm": "3045022100ad5913081023b6c6395910aeeb224e5e2918b002fa13dd541537d0d3f1eff92e022066907dd4cc78dee6a8447950a3b8aae23dae942c1a1b319b8da7e6faa42c59a701 032467318ba6bece08a4e9cb1e9c6243771dc4af83ccade82ada0d038ec86bf874"
                    },
                    "valueSat": 6796666782305
                }
            ],
            "txid": "caf1fc2430d3c0d5c0f6d0d68a0ea40ed8c3467006a85219a36531c070b49968",
            "fees": 0.00452,
            "blockhash": "eac47a6e978dcec1ec509bed55437cfb0eeba42f621acde8c8653ae068b68d14",
            "version": 2,
            "locktime": 1423343,
            "blocktime": 1535423464
        },
        {
            "time": 1535423464,
            "valueOut": 70471.27786305,
            "size": 226,
            "confirmations": 5179,
            "vout": [
                {
                    "scriptPubKey": {
                        "type": "pubkeyhash",
                        "asm": "OP_DUP OP_HASH160 0c4af7ff5e1f246bd138f65d7075bed311859c5c OP_EQUALVERIFY OP_CHECKSIG",
                        "addresses": [
                            "M92A9ek5745jKDveURpmKzagwe1pCDkVeM"
                        ],
                        "reqSigs": 1
                    },
                    "spentIndex": 2,
                    "spentTs": 1535521666,
                    "spentTxId": "80dc321149a4bd25cb17d87253e918422a08051b39830737c30a0b1e2912a206",
                    "n": 0,
                    "value": "834.86700000"
                },
                {
                    "scriptPubKey": {
                        "type": "pubkeyhash",
                        "asm": "OP_DUP OP_HASH160 3cc56f3359f9c1adb94479c0e2a17102a38dd284 OP_EQUALVERIFY OP_CHECKSIG",
                        "addresses": [
                            "MDSVHvNdqRYDqCWNaDKZcXEsUmjpbHMYFv"
                        ],
                        "reqSigs": 1
                    },
                    "spentIndex": 0,
                    "spentTs": 1535423464,
                    "spentTxId": "147baf62261ba8949c69081c3050d20f7cbb4a5cab915cc54915516f60d9a6d5",
                    "n": 1,
                    "value": "69636.41086305"
                }
            ],
            "valueIn": 70471.28238305,
            "vin": [
                {
                    "vout": 1,
                    "doubleSpentTxID": null,
                    "txid": "763bcdde63b7c3cae780310918f46f22d0d4d47069382da8e3d59b906df09515",
                    "addr": "MAT8jAxGPxUJrGzszPsdBg9Hrsy4frPWx5",
                    "value": 70471.28238305,
                    "sequence": 4294967294,
                    "n": 0,
                    "scriptSig": {
                        "asm": "3045022100f6e864b1edc7ab3819b5cc7df748a92691640227c431a885806c7214b210224202207d62c9fe13188af498ea5a0781a08b03a58329f50c65b37f8c0bf6968f71fc4101 0264b7c45ee07f35e7a5e97c42e1b291be10b56936a37b48a04880d0bcbf6cab43"
                    },
                    "valueSat": 7047128238305
                }
            ],
            "txid": "cc4833cff4ab1e28b6101cb62029f016dd67a2f5b592064957ce16fe96c08ab5",
            "fees": 0.00452,
            "blockhash": "eac47a6e978dcec1ec509bed55437cfb0eeba42f621acde8c8653ae068b68d14",
            "version": 2,
            "locktime": 1423343,
            "blocktime": 1535423464
        },
        {
            "time": 1535521666,
            "valueOut": 2504.6,
            "size": 520,
            "confirmations": 4129,
            "vout": [
                {
                    "scriptPubKey": {
                        "type": "pubkeyhash",
                        "asm": "OP_DUP OP_HASH160 89dbde79a6a3a218267376a8541d2ac9e89af735 OP_EQUALVERIFY OP_CHECKSIG",
                        "addresses": [
                            "MLU6CUnkgTQ6DWznDoN1Smog5R15iuZ9Uo"
                        ],
                        "reqSigs": 1
                    },
                    "spentIndex": 0,
                    "spentTs": 1535523233,
                    "spentTxId": "01deb38b2d9adf04d08b896b71f9d6cfe78e99c1ce71e2c26111bdbb8be115db",
                    "n": 0,
                    "value": "2000.00000000"
                },
                {
                    "scriptPubKey": {
                        "type": "pubkeyhash",
                        "asm": "OP_DUP OP_HASH160 aba25fa5781184a44317d5fb7072d948b40afa27 OP_EQUALVERIFY OP_CHECKSIG",
                        "addresses": [
                            "MPYgJ9eqeeqnTpB8Rdwmmu87abNKM76Fkx"
                        ],
                        "reqSigs": 1
                    },
                    "spentIndex": 5,
                    "spentTs": 1535526808,
                    "spentTxId": "2ea2b762296de0ada8bcbd79134370b5f24f7684d679e29321325b0fd87868dd",
                    "n": 1,
                    "value": "504.60000000"
                }
            ],
            "valueIn": 2504.601,
            "vin": [
                {
                    "vout": 0,
                    "doubleSpentTxID": null,
                    "txid": "fb6c291c0e4ebb74fbb48891aeb3b96de81d4b4137af18bedda7ef57968097ed",
                    "addr": "M92A9ek5745jKDveURpmKzagwe1pCDkVeM",
                    "value": 834.867,
                    "sequence": 4294967295,
                    "n": 0,
                    "scriptSig": {
                        "asm": "304402205fcbacb728e88ef04cac8b80327a6b80ef769f05cfd625435dbf7e6537405d4702204e326d8df19abf6d77ad6b54bcc77c0405d574fd83977afae219252e7f190dc301 0314b95e9b42ea325167b546087280e79de051cae2599a85389662b8a2d28720c3"
                    },
                    "valueSat": 83486700000
                },
                {
                    "vout": 1,
                    "doubleSpentTxID": null,
                    "txid": "f4547de754fe481bd9ad85c64a1736726a270b41d9c5164f47794d7c797a19e9",
                    "addr": "M92A9ek5745jKDveURpmKzagwe1pCDkVeM",
                    "value": 834.867,
                    "sequence": 4294967295,
                    "n": 1,
                    "scriptSig": {
                        "asm": "3045022100cad62942da4b68cac6d58ec4bc408e9b3a3a5fc4d94f4fa8a4e10fd5af0bd4da022060f03863f8ec7122485881d12c290a1ac9c190068f3a75902d8fffe82940cdc901 0314b95e9b42ea325167b546087280e79de051cae2599a85389662b8a2d28720c3"
                    },
                    "valueSat": 83486700000
                },
                {
                    "vout": 0,
                    "doubleSpentTxID": null,
                    "txid": "cc4833cff4ab1e28b6101cb62029f016dd67a2f5b592064957ce16fe96c08ab5",
                    "addr": "M92A9ek5745jKDveURpmKzagwe1pCDkVeM",
                    "value": 834.867,
                    "sequence": 4294967295,
                    "n": 2,
                    "scriptSig": {
                        "asm": "304402204cb0fbbd0775f84e126234f2eb944f2ab73e1ffac248b063fa727fbe0156f84602200e492b57982d7530e9fcc2e4c6134f24607c95e3f31bc7d539d48820f659feb901 0314b95e9b42ea325167b546087280e79de051cae2599a85389662b8a2d28720c3"
                    },
                    "valueSat": 83486700000
                }
            ],
            "txid": "80dc321149a4bd25cb17d87253e918422a08051b39830737c30a0b1e2912a206",
            "fees": 0.001,
            "blockhash": "c1764bdc4aba18ec31dc1cf779ae06bf3e3a54eb700c97f6423bb71b87f6cedb",
            "version": 1,
            "locktime": 0,
            "blocktime": 1535521666
        }
    ]
}